auto_vtna/Auto_VTNA_GUI.py
auto_vtna/Automatic_VTNA.py
auto_vtna/Normal_VTNA.py
auto_vtna/Same_Excess.py
auto_vtna/VTNA_functions.py
auto_vtna/__init__.py
auto_vtna-1.1.9.dist-info/licenses/LICENCE.md
auto_vtna-1.1.9.dist-info/METADATA
auto_vtna-1.1.9.dist-info/WHEEL
auto_vtna-1.1.9.dist-info/top_level.txt
auto_vtna-1.1.9.dist-info/RECORD
