Metadata-Version: 2.4
Name: auto_vtna
Version: 1.1.9
Summary: A Python package for efficient and automatic VTNA analysis
Author: Daniel Dalland
Author-email: Daniel Dalland <dd4518@ic.ac.uk>
Project-URL: Repository, https://github.com/ddalland/Auto-VTNA
Classifier: Programming Language :: Python :: 3
Classifier: Programming Language :: Python :: 3.6
Classifier: Programming Language :: Python :: 3.7
Classifier: Programming Language :: Python :: 3.8
Classifier: Programming Language :: Python :: 3.9
Classifier: Programming Language :: Python :: 3.10
Classifier: Programming Language :: Python :: 3.11
Requires-Python: >=3.6.0
License-File: LICENCE.md
Requires-Dist: pandas
Requires-Dist: numpy
Requires-Dist: matplotlib
Requires-Dist: num2words
Requires-Dist: mplcursors
Requires-Dist: scipy
Requires-Dist: polyfit
Requires-Dist: FreeSimpleGUI
Requires-Dist: openpyxl
Dynamic: author
Dynamic: license-file
Dynamic: requires-python
